setup.py
compressinja/__init__.py
compressinja/html.py
compressinja.egg-info/PKG-INFO
compressinja.egg-info/SOURCES.txt
compressinja.egg-info/dependency_links.txt
compressinja.egg-info/requires.txt
compressinja.egg-info/top_level.txt